obsidown/__init__.py
obsidown/__main__.py
obsidown/config.py
obsidown/main.py
obsidown/operations/base.py
obsidown/operations/citations.py
obsidown/operations/dispatch.py
obsidown/operations/link_convert.py
obsidown/operations/math_convert.py
obsidown/operations/remove_after_string.py
obsidown/operations/update_frontmatter.py
obsidown/operations/write_file.py
obsidown/utils.py
obsidown-0.2.8.dist-info/LICENSE
obsidown-0.2.8.dist-info/METADATA
obsidown-0.2.8.dist-info/WHEEL
obsidown-0.2.8.dist-info/RECORD
