Metadata-Version: 2.1
Name: obsidown
Version: 0.2.8
Summary: A quick way to convert obsidian markdown docs to markdown static pages
Home-page: https://pypi.org/project/obsidown/
License: GPL-3.0-only
Author: Angelo 'Flecart' Huang
Author-email: xuanqiang.huang@studio.unibo.it
Requires-Python: >=3.11,<4.0
Classifier: Development Status :: 2 - Pre-Alpha
Classifier: Environment :: Console
Classifier: Intended Audience :: Developers
Classifier: License :: OSI Approved :: GNU Affero General Public License v3
Classifier: License :: OSI Approved :: GNU General Public License v3 (GPLv3)
Classifier: Operating System :: OS Independent
Classifier: Programming Language :: Python :: 3
Classifier: Programming Language :: Python :: 3.11
Classifier: Programming Language :: Python :: 3.12
Requires-Dist: bibtexparser (>=2.0.0b7,<3.0.0)
Requires-Dist: gitpython (>=3.1.44,<4.0.0)
Requires-Dist: pydantic (>=2.6.3,<3.0.0)
Requires-Dist: python-frontmatter (>=1.1.0,<2.0.0)
Requires-Dist: pyyaml (>=6.0.1,<7.0.0)
Project-URL: Repository, https://github.com/flecart/obsidown
